rogue/__init__.py
rogue/main.py
rogue/controllers/__init__.py
rogue/controllers/base.py
rogue/controllers/engine.py
rogue/controllers/project.py
rogue/controllers/projects.py
rogue/controllers/utils.py
rogue/core/__init__.py
rogue/core/exc.py
rogue/core/version.py
rogue/ext/__init__.py
rogue/plugins/__init__.py
rogue/templates/__init__.py
rogue/templates/command1.jinja2
rogue/templates/msg.jinja2
rogue/templates/project.jinja2
rogue/templates/table.jinja2
rogue/templates/validate.jinja2
mutant_rogue-0.0.4.dist-info/LICENSE.md
mutant_rogue-0.0.4.dist-info/METADATA
mutant_rogue-0.0.4.dist-info/WHEEL
mutant_rogue-0.0.4.dist-info/entry_points.txt
mutant_rogue-0.0.4.dist-info/top_level.txt
mutant_rogue-0.0.4.dist-info/RECORD
