Metadata-Version: 2.1
Name: mutant-rogue
Version: 0.0.4
Summary: Rogue Cli
Home-page: https://bitbucket.org/unearsa/rogue-cli
Author: Pedrinho
Author-email: pedro.carvalho@mutantbr.com
License: unlicensed
Platform: UNKNOWN
Requires-Python: >=3.6
Requires-Dist: cement (==3.0.4)
Requires-Dist: jinja2
Requires-Dist: pyyaml
Requires-Dist: colorlog
Requires-Dist: pytest
Requires-Dist: pytest-cov
Requires-Dist: coverage
Requires-Dist: twine (>=1.11.0)
Requires-Dist: setuptools (>=38.6.0)
Requires-Dist: wheel (>=0.31.0)
Requires-Dist: requests (>=2.22.0)
Requires-Dist: termcolor (>=1.1.0)
Requires-Dist: tabulate (>=0.8.7)
